cloud_events/__init__.py
cloud_events/adapter.py
cloud_events/handler.py
cloud_events/interface.py
cloud_events/utils.py
cloud_events-0.3.0.dist-info/METADATA
cloud_events-0.3.0.dist-info/WHEEL
cloud_events-0.3.0.dist-info/top_level.txt
cloud_events-0.3.0.dist-info/RECORD
