Metadata-Version: 2.1
Name: cloud-events
Version: 0.3.0
Summary: Send CloudEvents (and AWS Events) to an ASGI or WSGI application
Author-email: Kyle Hornberg <kyle.hornberg@gmail.com>
License: MIT license
Project-URL: Homepage, https://github.com/khornberg/cloud-events-handler
Project-URL: Documentation, https://github.com/khornberg/cloud-events-handler
Project-URL: Repository, https://github.com/khornberg/cloud-events-handler.git
Keywords: cloudevents,serverless,wsgi,asgi,aws,azure
Classifier: Development Status :: 4 - Beta
Classifier: Intended Audience :: Developers
Classifier: License :: OSI Approved :: MIT License
Classifier: Operating System :: Unix
Classifier: Operating System :: POSIX
Classifier: Operating System :: Microsoft :: Windows
Classifier: Programming Language :: Python
Classifier: Programming Language :: Python :: 3
Classifier: Programming Language :: Python :: 3.8
Classifier: Programming Language :: Python :: 3.11
Classifier: Programming Language :: Python :: 3.12
Classifier: Programming Language :: Python :: Implementation :: CPython
Classifier: Topic :: Utilities
Requires-Python: >=3.8
Requires-Dist: werkzeug >=0.16.0
Requires-Dist: mangum <0.18.0,>=0.17.0
